spectate/__init__.py
spectate/base.py
spectate/events.py
spectate/models.py
spectate/mvc.py
spectate/py.typed
spectate/utils.py
spectate-1.0.1.dist-info/LICENSE
spectate-1.0.1.dist-info/METADATA
spectate-1.0.1.dist-info/WHEEL
spectate-1.0.1.dist-info/top_level.txt
spectate-1.0.1.dist-info/RECORD
