Metadata-Version: 2.1
Name: spectate
Version: 1.0.1
Summary: Track changes to mutable data types.
Home-page: https://github.com/rmorshea/spectate
Author: Ryan Morshead
Author-email: ryan.morshead@gmail.com
License: MIT
Keywords: eventful,callbacks,mutable,MVC,model,view,controller
Platform: Linux
Platform: Mac OS X
Platform: Windows
Classifier: Intended Audience :: Developers
Requires-Python: >=3.6
